aniworld/ASCII.txt
aniworld/__init__.py
aniworld/__main__.py
aniworld/ascii_art.py
aniworld/config.py
aniworld/entry.py
aniworld/execute.py
aniworld/menu.py
aniworld/models.py
aniworld/parser.py
aniworld/search.py
aniworld/action/__init__.py
aniworld/action/common.py
aniworld/action/download.py
aniworld/action/syncplay.py
aniworld/action/watch.py
aniworld/anime4k/__init__.py
aniworld/anime4k/anime4k.py
aniworld/aniskip/__init__.py
aniworld/aniskip/aniskip.py
aniworld/aniskip/scripts/aniskip.lua
aniworld/aniskip/scripts/autoexit.lua
aniworld/aniskip/scripts/autostart.lua
aniworld/common/__init__.py
aniworld/common/common.py
aniworld/extractors/__init__.py
aniworld/extractors/test_providers.py
aniworld/extractors/provider/common.py
aniworld/extractors/provider/doodstream.py
aniworld/extractors/provider/filemoon.py
aniworld/extractors/provider/hanime.py
aniworld/extractors/provider/loadx.py
aniworld/extractors/provider/luluvdo.py
aniworld/extractors/provider/speedfiles.py
aniworld/extractors/provider/streamtape.py
aniworld/extractors/provider/vidmoly.py
aniworld/extractors/provider/vidoza.py
aniworld/extractors/provider/voe.py
aniworld/nuitka/preprocess.py
aniworld/web/__init__.py
aniworld/web/app.py
aniworld/web/database.py
aniworld/web/download_manager.py
aniworld/web/static/css/style.css
aniworld/web/static/js/app.js
aniworld/web/templates/index.html
aniworld/web/templates/login.html
aniworld/web/templates/settings.html
aniworld/web/templates/setup.html
aniworld-3.8.2.dist-info/licenses/LICENSE
aniworld-3.8.2.dist-info/METADATA
aniworld-3.8.2.dist-info/WHEEL
aniworld-3.8.2.dist-info/entry_points.txt
aniworld-3.8.2.dist-info/top_level.txt
aniworld-3.8.2.dist-info/RECORD
