Metadata-Version: 2.4
Name: aniworld
Version: 3.8.2
Summary: AniWorld Downloader is a command-line tool for downloading and streaming anime, series and movies, compatible with Windows, macOS, and Linux.
Author-email: Phoenixthrush UwU <contact@phoenixthrush.com>
Maintainer-email: Phoenixthrush UwU <contact@phoenixthrush.com>
License: MIT
Project-URL: Homepage, https://github.com/phoenixthrush/AniWorld-Downloader
Project-URL: Documentation, https://github.com/phoenixthrush/AniWorld-Downloader/blob/main/README.md
Project-URL: Repository, https://github.com/phoenixthrush/AniWorld-Downloader.git
Project-URL: Bug Tracker, https://github.com/phoenixthrush/AniWorld-Downloader/issues
Project-URL: Changelog, https://github.com/phoenixthrush/AniWorld-Downloader/commits
Project-URL: Source Code, https://github.com/phoenixthrush/AniWorld-Downloader
Project-URL: Download, https://github.com/phoenixthrush/AniWorld-Downloader/archive/refs/heads/main.zip
Project-URL: Funding, https://github.com/sponsors/phoenixthrush
Keywords: anime,aniworld,anime-downloader,aniworld-downloader,streaming,download,video,multimedia,cli
Classifier: Development Status :: 5 - Production/Stable
Classifier: Environment :: Console
Classifier: Intended Audience :: End Users/Desktop
Classifier: License :: OSI Approved :: MIT License
Classifier: Natural Language :: English
Classifier: Operating System :: OS Independent
Classifier: Operating System :: Microsoft :: Windows
Classifier: Operating System :: POSIX :: Linux
Classifier: Operating System :: MacOS
Classifier: Programming Language :: Python :: 3
Classifier: Programming Language :: Python :: 3.9
Classifier: Programming Language :: Python :: 3.10
Classifier: Programming Language :: Python :: 3.11
Classifier: Programming Language :: Python :: 3.12
Classifier: Programming Language :: Python :: 3.13
Classifier: Programming Language :: Python :: 3 :: Only
Classifier: Topic :: Internet :: WWW/HTTP :: Dynamic Content
Classifier: Topic :: Multimedia
Classifier: Topic :: Multimedia :: Sound/Audio
Classifier: Topic :: Multimedia :: Video
Classifier: Topic :: Multimedia :: Video :: Display
Classifier: Topic :: Software Development :: Libraries :: Python Modules
Classifier: Topic :: System :: Archiving
Classifier: Topic :: Utilities
Classifier: Typing :: Typed
Requires-Python: >=3.9
License-File: LICENSE
Requires-Dist: requests
Requires-Dist: bs4
Requires-Dist: yt-dlp
Requires-Dist: npyscreen
Requires-Dist: tqdm
Requires-Dist: fake_useragent
Requires-Dist: packaging
Requires-Dist: jsbeautifier
Requires-Dist: flask
Requires-Dist: py-cpuinfo; platform_system == "Windows"
Requires-Dist: windows-curses; platform_system == "Windows"
Requires-Dist: winfcntl; platform_system == "Windows"
Dynamic: license-file
